{
    "version":  "2.1.56",
    "build":  122,
    "downloadUrl":  "https://github.com/iibrahim27/satinalma-pro/releases/download/v2.1.56/SatinalmaPro_Kurulum.exe",
    "downloadUrlZip":  "https://github.com/iibrahim27/satinalma-pro/releases/download/v2.1.56/SatinalmaPro.zip",
    "downloadUrlApk":  "https://github.com/iibrahim27/satinalma-pro/releases/download/v2.1.56/SatinalmaPro.apk",
    "notes":  "Teklif Kaydet hucre commit; Acil teklif iste yok; Satinalma/Yonetim onay-red-revize butonlari",
    "zorunlu":  false
}
